[
    {
        "Full Name": "Daniel Brown",
        "Email Address": "ahale@hotmail.com",
        "Phone Number": "244-169-5801x7072",
        "Organization/Company": "Wells-Wilson",
        "Workshop Category": "Finance & Investment",
        "Preferred Session Date": "2025/02/02",
        "Preferred Time Slot": "6PM",
        "Preferred Delivery Mode": "Hybrid",
        "Highest Education Level": "Master's Degree",
        "Years of Professional Experience": 20,
        "Current Role/Position": "Armed forces training and education officer",
        "Dietary Requirements": "Halal",
        "Accessibility Requirements": "None",
        "Payment Method": "Company Sponsored",
        "Billing Address": "USS Gonzalez\nFPO AE 24907",
        "What do you hope to learn from this workshop?": "I would like to improve my leadership and communication skills to manage my team more effectively.",
        "Any other special requests or comments?": "I would like to see examples of successful leadership strategies in small and medium-sized businesses."
    },
    {
        "Full Name": "Patrick Martinez",
        "Email Address": "staceysnyder@gmail.com",
        "Phone Number": "452.094.8272x557",
        "Organization/Company": "Sutton Ltd",
        "Workshop Category": "Technology & IT",
        "Preferred Session Date": "2025/01/24",
        "Preferred Time Slot": "8PM",
        "Preferred Delivery Mode": "In-Person",
        "Highest Education Level": "PhD",
        "Years of Professional Experience": 19,
        "Current Role/Position": "Television camera operator",
        "Dietary Requirements": "None",
        "Accessibility Requirements": "None",
        "Payment Method": "Company Sponsored",
        "Billing Address": "5356 Taylor Lane\nPort Patricia, NC 43042",
        "What do you hope to learn from this workshop?": "I look forward to learning effective strategies for improving productivity and leading successful teams.",
        "Any other special requests or comments?": "I would appreciate it if the workshop could include some real-life case studies or examples."
    },
    {
        "Full Name": "Ariel Johnson",
        "Email Address": "morrisbrianna@nguyen.com",
        "Phone Number": "7017845441",
        "Organization/Company": "Ho, Dudley and Hill",
        "Workshop Category": "Technology & IT",
        "Preferred Session Date": "2025/01/17",
        "Preferred Time Slot": "7PM",
        "Preferred Delivery Mode": "In-Person",
        "Highest Education Level": "Associate Degree",
        "Years of Professional Experience": 20,
        "Current Role/Position": "Surgeon",
        "Dietary Requirements": "Vegetarian",
        "Accessibility Requirements": "None",
        "Payment Method": "Company Sponsored",
        "Billing Address": "720 Dougherty Neck Apt. 378\nEast Danielleton, NJ 98906",
        "What do you hope to learn from this workshop?": "I look forward to learning effective strategies for improving productivity and leading successful teams.",
        "Any other special requests or comments?": "I am particularly interested in understanding how to develop an effective digital marketing strategy for a startup."
    },
    {
        "Full Name": "Caleb Taylor",
        "Email Address": "bhenry@wright-turner.com",
        "Phone Number": "949-868-9833x895",
        "Organization/Company": "Brooks, Nunez and Combs",
        "Workshop Category": "Finance & Investment",
        "Preferred Session Date": "2025/02/12",
        "Preferred Time Slot": "2PM",
        "Preferred Delivery Mode": "In-Person",
        "Highest Education Level": "Bachelor's Degree",
        "Years of Professional Experience": 2,
        "Current Role/Position": "Programmer, applications",
        "Dietary Requirements": "Vegetarian",
        "Accessibility Requirements": "None",
        "Payment Method": "Bank Transfer",
        "Billing Address": "110 Ingram Roads Suite 007\nCollierfurt, AZ 01599",
        "What do you hope to learn from this workshop?": "I am looking forward to learning the latest trends in IT management and how to integrate them into our business.",
        "Any other special requests or comments?": "It would be great if we could have a session on the integration of modern technologies with traditional business models."
    },
    {
        "Full Name": "Michelle Griffin",
        "Email Address": "wilsonjoseph@hotmail.com",
        "Phone Number": "001-394-877-0930x187",
        "Organization/Company": "Carlson, Horton and Bonilla",
        "Workshop Category": "Finance & Investment",
        "Preferred Session Date": "2025/02/02",
        "Preferred Time Slot": "morning",
        "Preferred Delivery Mode": "Hybrid",
        "Highest Education Level": "PhD",
        "Years of Professional Experience": 9,
        "Current Role/Position": "Production assistant, television",
        "Dietary Requirements": "None",
        "Accessibility Requirements": "None",
        "Payment Method": "Company Sponsored",
        "Billing Address": "10555 George Squares Apt. 993\nDavidmouth, MA 52312",
        "What do you hope to learn from this workshop?": "I am interested in exploring financial tools and models that can help optimize business growth.",
        "Any other special requests or comments?": "I am particularly interested in hands-on learning opportunities and would prefer an interactive format."
    },
    {
        "Full Name": "Veronica Williams",
        "Email Address": "carolynjenkins@thomas-franco.com",
        "Phone Number": "(268)027-7549",
        "Organization/Company": "Nguyen-Rodriguez",
        "Workshop Category": "Technology & IT",
        "Preferred Session Date": "2025/01/20",
        "Preferred Time Slot": "9PM",
        "Preferred Delivery Mode": "In-Person",
        "Highest Education Level": "PhD",
        "Years of Professional Experience": 7,
        "Current Role/Position": "Actuary",
        "Dietary Requirements": "Other (Please specify)",
        "Accessibility Requirements": "None",
        "Payment Method": "Bank Transfer",
        "Billing Address": "4675 Cox Knolls Suite 710\nLake Abigailchester, SD 75142",
        "What do you hope to learn from this workshop?": "I hope to gain a deeper understanding of digital marketing strategies to improve our company's online presence.",
        "Any other special requests or comments?": "It would be great if we could have a session on the integration of modern technologies with traditional business models."
    },
    {
        "Full Name": "Vincent Grant",
        "Email Address": "wadejustin@hotmail.com",
        "Phone Number": "750-539-9898x847",
        "Organization/Company": "Clark Inc",
        "Workshop Category": "Finance & Investment",
        "Preferred Session Date": "2025/01/13",
        "Preferred Time Slot": "evening",
        "Preferred Delivery Mode": "Hybrid",
        "Highest Education Level": "High School",
        "Years of Professional Experience": 11,
        "Current Role/Position": "Archivist",
        "Dietary Requirements": "Vegan",
        "Accessibility Requirements": "None",
        "Payment Method": "Company Sponsored",
        "Billing Address": "030 Patrick Lane Apt. 863\nLake Williambury, GA 88207",
        "What do you hope to learn from this workshop?": "I hope to gain a deeper understanding of digital marketing strategies to improve our company's online presence.",
        "Any other special requests or comments?": "Please consider providing more information on the practical applications of digital marketing in different industries."
    },
    {
        "Full Name": "Phyllis Medina",
        "Email Address": "millsjeanne@york.com",
        "Phone Number": "+1-258-925-2056x7450",
        "Organization/Company": "Miller-Lam",
        "Workshop Category": "Digital Marketing",
        "Preferred Session Date": "2025/01/10",
        "Preferred Time Slot": "afternoon",
        "Preferred Delivery Mode": "In-Person",
        "Highest Education Level": "Associate Degree",
        "Years of Professional Experience": 14,
        "Current Role/Position": "Ecologist",
        "Dietary Requirements": "Other (Please specify)",
        "Accessibility Requirements": "None",
        "Payment Method": "Company Sponsored",
        "Billing Address": "1128 Amanda Oval Suite 911\nBradychester, ME 18935",
        "What do you hope to learn from this workshop?": "I want to enhance my digital marketing knowledge to build stronger brand strategies and reach a wider audience.",
        "Any other special requests or comments?": "Please consider providing more information on the practical applications of digital marketing in different industries."
    },
    {
        "Full Name": "Eric Olson",
        "Email Address": "amber19@singleton.com",
        "Phone Number": "(022)021-1423x48208",
        "Organization/Company": "Young, Smith and Torres",
        "Workshop Category": "Finance & Investment",
        "Preferred Session Date": "2025/01/18",
        "Preferred Time Slot": "afternoon",
        "Preferred Delivery Mode": "In-Person",
        "Highest Education Level": "High School",
        "Years of Professional Experience": 11,
        "Current Role/Position": "Broadcast journalist",
        "Dietary Requirements": "Halal",
        "Accessibility Requirements": "None",
        "Payment Method": "Credit Card",
        "Billing Address": "3172 Davis Radial\nNew Shannonbury, CT 05671",
        "What do you hope to learn from this workshop?": "I would like to improve my leadership and communication skills to manage my team more effectively.",
        "Any other special requests or comments?": "I would like to see examples of successful leadership strategies in small and medium-sized businesses."
    },
    {
        "Full Name": "Tracy Bell",
        "Email Address": "hayesmarissa@carr.net",
        "Phone Number": "001-815-387-6045x44798",
        "Organization/Company": "Smith, Lopez and Garrett",
        "Workshop Category": "Business & Management",
        "Preferred Session Date": "2025/01/19",
        "Preferred Time Slot": "12PM",
        "Preferred Delivery Mode": "In-Person",
        "Highest Education Level": "Master's Degree",
        "Years of Professional Experience": 8,
        "Current Role/Position": "Marketing executive",
        "Dietary Requirements": "Kosher",
        "Accessibility Requirements": "None",
        "Payment Method": "Bank Transfer",
        "Billing Address": "9856 Tara Parks\nNicoleton, OR 93221",
        "What do you hope to learn from this workshop?": "I wish to learn more about how to manage and lead teams in dynamic work environments.",
        "Any other special requests or comments?": "I am particularly interested in understanding how to develop an effective digital marketing strategy for a startup."
    },
    {
        "Full Name": "Austin Cisneros",
        "Email Address": "michael75@christensen.net",
        "Phone Number": "001-694-683-8209x72990",
        "Organization/Company": "Dorsey Group",
        "Workshop Category": "Finance & Investment",
        "Preferred Session Date": "2025/01/30",
        "Preferred Time Slot": "2PM",
        "Preferred Delivery Mode": "Hybrid",
        "Highest Education Level": "PhD",
        "Years of Professional Experience": 16,
        "Current Role/Position": "Armed forces logistics/support/administrative officer",
        "Dietary Requirements": "None",
        "Accessibility Requirements": "None",
        "Payment Method": "Credit Card",
        "Billing Address": "000 Joshua Hollow Apt. 995\nFigueroaville, CO 92029",
        "What do you hope to learn from this workshop?": "I am seeking to improve my understanding of technology and its application in our marketing campaigns.",
        "Any other special requests or comments?": "It would be helpful if we could have some materials to review after the workshop to continue learning."
    },
    {
        "Full Name": "Jason Mooney",
        "Email Address": "nwallace@hotmail.com",
        "Phone Number": "001-870-621-2411x074",
        "Organization/Company": "Butler-Barry",
        "Workshop Category": "Business & Management",
        "Preferred Session Date": "2025/01/15",
        "Preferred Time Slot": "5PM",
        "Preferred Delivery Mode": "Hybrid",
        "Highest Education Level": "PhD",
        "Years of Professional Experience": 16,
        "Current Role/Position": "Research scientist (physical sciences)",
        "Dietary Requirements": "Vegan",
        "Accessibility Requirements": "None",
        "Payment Method": "Bank Transfer",
        "Billing Address": "989 Gregory Junction Suite 451\nPort Christopher, NV 62629",
        "What do you hope to learn from this workshop?": "I am excited to learn new skills in business management to better handle operational challenges.",
        "Any other special requests or comments?": "I would like to see examples of successful leadership strategies in small and medium-sized businesses."
    },
    {
        "Full Name": "Kyle Anderson",
        "Email Address": "darrengray@gilbert.com",
        "Phone Number": "1983191784",
        "Organization/Company": "Lewis-Bowman",
        "Workshop Category": "Digital Marketing",
        "Preferred Session Date": "2025/01/12",
        "Preferred Time Slot": "3PM",
        "Preferred Delivery Mode": "Hybrid",
        "Highest Education Level": "Bachelor's Degree",
        "Years of Professional Experience": 25,
        "Current Role/Position": "Research officer, political party",
        "Dietary Requirements": "Vegan",
        "Accessibility Requirements": "None",
        "Payment Method": "Bank Transfer",
        "Billing Address": "53441 Macdonald Place Suite 202\nWest Ernestside, IL 81092",
        "What do you hope to learn from this workshop?": "I wish to learn more about how to manage and lead teams in dynamic work environments.",
        "Any other special requests or comments?": "I would appreciate it if the workshop could include some real-life case studies or examples."
    },
    {
        "Full Name": "Paula Gibson PhD",
        "Email Address": "michaeldelgado@perry.info",
        "Phone Number": "(080)111-1819",
        "Organization/Company": "Lyons Group",
        "Workshop Category": "Technology & IT",
        "Preferred Session Date": "2025/02/11",
        "Preferred Time Slot": "6PM",
        "Preferred Delivery Mode": "Online",
        "Highest Education Level": "PhD",
        "Years of Professional Experience": 4,
        "Current Role/Position": "Comptroller",
        "Dietary Requirements": "Other (Please specify)",
        "Accessibility Requirements": "None",
        "Payment Method": "Company Sponsored",
        "Billing Address": "9037 Susan Mill\nEast Alexander, TN 40340",
        "What do you hope to learn from this workshop?": "I am interested in exploring financial tools and models that can help optimize business growth.",
        "Any other special requests or comments?": "It would be helpful if we could have some materials to review after the workshop to continue learning."
    },
    {
        "Full Name": "Megan Jordan",
        "Email Address": "jessicabrown@dixon.net",
        "Phone Number": "(571)248-8716x5178",
        "Organization/Company": "Chen, Hester and Lee",
        "Workshop Category": "Leadership & Communication",
        "Preferred Session Date": "2025/01/11",
        "Preferred Time Slot": "5PM",
        "Preferred Delivery Mode": "Online",
        "Highest Education Level": "High School",
        "Years of Professional Experience": 1,
        "Current Role/Position": "Financial planner",
        "Dietary Requirements": "Kosher",
        "Accessibility Requirements": "None",
        "Payment Method": "Credit Card",
        "Billing Address": "6304 Thomas Pass Apt. 179\nNew Nicoleshire, CT 32214",
        "What do you hope to learn from this workshop?": "I want to enhance my digital marketing knowledge to build stronger brand strategies and reach a wider audience.",
        "Any other special requests or comments?": "It would be beneficial to include some practical advice on managing financial risks and investments."
    },
    {
        "Full Name": "Brandon Armstrong",
        "Email Address": "leonardsmith@weiss.biz",
        "Phone Number": "+1-755-874-6247x94542",
        "Organization/Company": "Walls-Taylor",
        "Workshop Category": "Leadership & Communication",
        "Preferred Session Date": "2025/01/27",
        "Preferred Time Slot": "morning",
        "Preferred Delivery Mode": "Hybrid",
        "Highest Education Level": "Associate Degree",
        "Years of Professional Experience": 2,
        "Current Role/Position": "Production designer, theatre/television/film",
        "Dietary Requirements": "Other (Please specify)",
        "Accessibility Requirements": "None",
        "Payment Method": "Bank Transfer",
        "Billing Address": "437 Santiago Mountain\nConniebury, FL 47764",
        "What do you hope to learn from this workshop?": "I look forward to learning effective strategies for improving productivity and leading successful teams.",
        "Any other special requests or comments?": "It would be great if we could have a session on the integration of modern technologies with traditional business models."
    },
    {
        "Full Name": "Hannah Hawkins",
        "Email Address": "ymckay@hotmail.com",
        "Phone Number": "(247)243-4832x63504",
        "Organization/Company": "Holt, Mcdonald and Kelly",
        "Workshop Category": "Business & Management",
        "Preferred Session Date": "2025/01/30",
        "Preferred Time Slot": "8PM",
        "Preferred Delivery Mode": "Hybrid",
        "Highest Education Level": "Master's Degree",
        "Years of Professional Experience": 4,
        "Current Role/Position": "Microbiologist",
        "Dietary Requirements": "Kosher",
        "Accessibility Requirements": "None",
        "Payment Method": "Bank Transfer",
        "Billing Address": "09671 Davis Cliffs Suite 204\nSantosbury, IN 05279",
        "What do you hope to learn from this workshop?": "I hope to acquire knowledge about investment strategies and financial planning for better decision-making in business.",
        "Any other special requests or comments?": "I would like to see examples of successful leadership strategies in small and medium-sized businesses."
    },
    {
        "Full Name": "Jeremy Horton",
        "Email Address": "jeffreyjennings@cordova-hubbard.com",
        "Phone Number": "+1-691-246-6417x91749",
        "Organization/Company": "Kim LLC",
        "Workshop Category": "Digital Marketing",
        "Preferred Session Date": "2025/02/07",
        "Preferred Time Slot": "12PM",
        "Preferred Delivery Mode": "Online",
        "Highest Education Level": "PhD",
        "Years of Professional Experience": 5,
        "Current Role/Position": "Forensic psychologist",
        "Dietary Requirements": "None",
        "Accessibility Requirements": "None",
        "Payment Method": "Bank Transfer",
        "Billing Address": "59694 Carr Rest Suite 491\nMelindaton, IL 74019",
        "What do you hope to learn from this workshop?": "I would like to improve my leadership and communication skills to manage my team more effectively.",
        "Any other special requests or comments?": "I would appreciate it if the workshop could include some real-life case studies or examples."
    },
    {
        "Full Name": "Melissa Zamora",
        "Email Address": "thompsonjeffrey@strickland-jackson.com",
        "Phone Number": "(908)679-3416x71512",
        "Organization/Company": "Chambers-Allen",
        "Workshop Category": "Business & Management",
        "Preferred Session Date": "2025/01/16",
        "Preferred Time Slot": "afternoon",
        "Preferred Delivery Mode": "In-Person",
        "Highest Education Level": "High School",
        "Years of Professional Experience": 4,
        "Current Role/Position": "Sports administrator",
        "Dietary Requirements": "Vegetarian",
        "Accessibility Requirements": "None",
        "Payment Method": "Company Sponsored",
        "Billing Address": "4787 Christine Way\nNorth Carly, IA 39623",
        "What do you hope to learn from this workshop?": "I wish to learn more about how to manage and lead teams in dynamic work environments.",
        "Any other special requests or comments?": "I am particularly interested in understanding how to develop an effective digital marketing strategy for a startup."
    },
    {
        "Full Name": "Franklin Boyd",
        "Email Address": "christinefletcher@gray-smith.com",
        "Phone Number": "7689252134",
        "Organization/Company": "Brown-Jenkins",
        "Workshop Category": "Leadership & Communication",
        "Preferred Session Date": "2025/01/12",
        "Preferred Time Slot": "4PM",
        "Preferred Delivery Mode": "In-Person",
        "Highest Education Level": "PhD",
        "Years of Professional Experience": 18,
        "Current Role/Position": "Health promotion specialist",
        "Dietary Requirements": "Vegan",
        "Accessibility Requirements": "None",
        "Payment Method": "Company Sponsored",
        "Billing Address": "804 Wilson Lake Suite 932\nSouth Graceborough, WA 94267",
        "What do you hope to learn from this workshop?": "I wish to learn more about how to manage and lead teams in dynamic work environments.",
        "Any other special requests or comments?": "It would be helpful if we could have some materials to review after the workshop to continue learning."
    },
    {
        "Full Name": "Megan Watkins",
        "Email Address": "walterramos@yahoo.com",
        "Phone Number": "001-227-004-4459x965",
        "Organization/Company": "Brown-Castillo",
        "Workshop Category": "Leadership & Communication",
        "Preferred Session Date": "2025/02/11",
        "Preferred Time Slot": "10AM",
        "Preferred Delivery Mode": "In-Person",
        "Highest Education Level": "Associate Degree",
        "Years of Professional Experience": 14,
        "Current Role/Position": "Regulatory affairs officer",
        "Dietary Requirements": "None",
        "Accessibility Requirements": "None",
        "Payment Method": "Company Sponsored",
        "Billing Address": "02050 Young Summit Apt. 952\nNew Angie, NE 23917",
        "What do you hope to learn from this workshop?": "I am excited to learn new skills in business management to better handle operational challenges.",
        "Any other special requests or comments?": "It would be great if we could have a session on the integration of modern technologies with traditional business models."
    },
    {
        "Full Name": "Katelyn Williamson",
        "Email Address": "heathermiller@gmail.com",
        "Phone Number": "(862)401-2024x601",
        "Organization/Company": "Wagner-Mejia",
        "Workshop Category": "Business & Management",
        "Preferred Session Date": "2025/02/06",
        "Preferred Time Slot": "10AM",
        "Preferred Delivery Mode": "Hybrid",
        "Highest Education Level": "Associate Degree",
        "Years of Professional Experience": 9,
        "Current Role/Position": "Health and safety inspector",
        "Dietary Requirements": "Halal",
        "Accessibility Requirements": "None",
        "Payment Method": "Company Sponsored",
        "Billing Address": "747 Michelle Station Suite 407\nDouglaston, VA 47732",
        "What do you hope to learn from this workshop?": "I want to enhance my digital marketing knowledge to build stronger brand strategies and reach a wider audience.",
        "Any other special requests or comments?": "I would prefer to focus on team-building strategies and techniques that can improve collaboration in diverse teams."
    },
    {
        "Full Name": "Mathew Ramos",
        "Email Address": "itaylor@george.com",
        "Phone Number": "578.645.7607",
        "Organization/Company": "Hernandez-Spencer",
        "Workshop Category": "Technology & IT",
        "Preferred Session Date": "2025/01/30",
        "Preferred Time Slot": "5PM",
        "Preferred Delivery Mode": "Hybrid",
        "Highest Education Level": "Bachelor's Degree",
        "Years of Professional Experience": 18,
        "Current Role/Position": "Warehouse manager",
        "Dietary Requirements": "Kosher",
        "Accessibility Requirements": "None",
        "Payment Method": "Company Sponsored",
        "Billing Address": "6364 Kathryn Branch Suite 287\nChristinashire, DE 94348",
        "What do you hope to learn from this workshop?": "I am excited to learn new skills in business management to better handle operational challenges.",
        "Any other special requests or comments?": "It would be beneficial to include some practical advice on managing financial risks and investments."
    },
    {
        "Full Name": "Justin Chavez",
        "Email Address": "rmoss@smith.org",
        "Phone Number": "552.050.8178x103",
        "Organization/Company": "Hanson, Kane and Khan",
        "Workshop Category": "Digital Marketing",
        "Preferred Session Date": "2025/01/01",
        "Preferred Time Slot": "morning",
        "Preferred Delivery Mode": "In-Person",
        "Highest Education Level": "PhD",
        "Years of Professional Experience": 19,
        "Current Role/Position": "Engineer, aeronautical",
        "Dietary Requirements": "Vegetarian",
        "Accessibility Requirements": "None",
        "Payment Method": "Bank Transfer",
        "Billing Address": "95729 Parks Isle\nJamesfurt, NH 32085",
        "What do you hope to learn from this workshop?": "I am excited to learn new skills in business management to better handle operational challenges.",
        "Any other special requests or comments?": "It would be great if we could have a session on the integration of modern technologies with traditional business models."
    },
    {
        "Full Name": "Andrew Chen",
        "Email Address": "gerald19@gmail.com",
        "Phone Number": "082.761.0978",
        "Organization/Company": "Ochoa-Lawson",
        "Workshop Category": "Business & Management",
        "Preferred Session Date": "2025/01/27",
        "Preferred Time Slot": "evening",
        "Preferred Delivery Mode": "In-Person",
        "Highest Education Level": "PhD",
        "Years of Professional Experience": 4,
        "Current Role/Position": "Waste management officer",
        "Dietary Requirements": "Vegetarian",
        "Accessibility Requirements": "None",
        "Payment Method": "Credit Card",
        "Billing Address": "982 Davis Vista Suite 809\nEast Cassie, AL 91196",
        "What do you hope to learn from this workshop?": "I am interested in exploring financial tools and models that can help optimize business growth.",
        "Any other special requests or comments?": "I would prefer to focus on team-building strategies and techniques that can improve collaboration in diverse teams."
    },
    {
        "Full Name": "Julie Hahn",
        "Email Address": "hillanthony@yahoo.com",
        "Phone Number": "814.912.1698",
        "Organization/Company": "Lawrence, Harrison and Ross",
        "Workshop Category": "Leadership & Communication",
        "Preferred Session Date": "2025/01/03",
        "Preferred Time Slot": "5PM",
        "Preferred Delivery Mode": "Online",
        "Highest Education Level": "High School",
        "Years of Professional Experience": 6,
        "Current Role/Position": "Data scientist",
        "Dietary Requirements": "Halal",
        "Accessibility Requirements": "None",
        "Payment Method": "Company Sponsored",
        "Billing Address": "030 Vasquez Crossing Suite 486\nBradleytown, NV 05074",
        "What do you hope to learn from this workshop?": "I hope to gain a deeper understanding of digital marketing strategies to improve our company's online presence.",
        "Any other special requests or comments?": "It would be great if we could have a session on the integration of modern technologies with traditional business models."
    },
    {
        "Full Name": "Nathan Garcia",
        "Email Address": "lori36@yahoo.com",
        "Phone Number": "7400227183",
        "Organization/Company": "Bartlett-Noble",
        "Workshop Category": "Leadership & Communication",
        "Preferred Session Date": "2025/01/24",
        "Preferred Time Slot": "12PM",
        "Preferred Delivery Mode": "Online",
        "Highest Education Level": "Master's Degree",
        "Years of Professional Experience": 18,
        "Current Role/Position": "Technical sales engineer",
        "Dietary Requirements": "None",
        "Accessibility Requirements": "None",
        "Payment Method": "Credit Card",
        "Billing Address": "20534 Stephanie Viaduct\nDonnafurt, MO 04042",
        "What do you hope to learn from this workshop?": "I am excited to learn new skills in business management to better handle operational challenges.",
        "Any other special requests or comments?": "I would prefer to focus on team-building strategies and techniques that can improve collaboration in diverse teams."
    },
    {
        "Full Name": "Thomas Baker",
        "Email Address": "hugheslawrence@gmail.com",
        "Phone Number": "(451)502-8697x3436",
        "Organization/Company": "Calderon Ltd",
        "Workshop Category": "Digital Marketing",
        "Preferred Session Date": "2025/01/24",
        "Preferred Time Slot": "8PM",
        "Preferred Delivery Mode": "In-Person",
        "Highest Education Level": "Master's Degree",
        "Years of Professional Experience": 7,
        "Current Role/Position": "Associate Professor",
        "Dietary Requirements": "None",
        "Accessibility Requirements": "None",
        "Payment Method": "Credit Card",
        "Billing Address": "97627 Donna Fork Suite 206\nCurtischester, LA 56174",
        "What do you hope to learn from this workshop?": "I hope to acquire knowledge about investment strategies and financial planning for better decision-making in business.",
        "Any other special requests or comments?": "I am particularly interested in hands-on learning opportunities and would prefer an interactive format."
    },
    {
        "Full Name": "Jeremy Fitzgerald",
        "Email Address": "oliverandrew@singleton.com",
        "Phone Number": "(731)335-3367x792",
        "Organization/Company": "Contreras, Ramsey and Edwards",
        "Workshop Category": "Technology & IT",
        "Preferred Session Date": "2025/02/16",
        "Preferred Time Slot": "2PM",
        "Preferred Delivery Mode": "Hybrid",
        "Highest Education Level": "PhD",
        "Years of Professional Experience": 15,
        "Current Role/Position": "Geneticist, molecular",
        "Dietary Requirements": "Other (Please specify)",
        "Accessibility Requirements": "None",
        "Payment Method": "Bank Transfer",
        "Billing Address": "85480 Gonzalez Creek Apt. 294\nOconnorstad, KS 21983",
        "What do you hope to learn from this workshop?": "I hope to gain a deeper understanding of digital marketing strategies to improve our company's online presence.",
        "Any other special requests or comments?": "I would appreciate it if the workshop could include some real-life case studies or examples."
    },
    {
        "Full Name": "Clifford Taylor",
        "Email Address": "morganantonio@morgan.net",
        "Phone Number": "8212261496",
        "Organization/Company": "Peters LLC",
        "Workshop Category": "Leadership & Communication",
        "Preferred Session Date": "2025/01/27",
        "Preferred Time Slot": "10AM",
        "Preferred Delivery Mode": "Online",
        "Highest Education Level": "Master's Degree",
        "Years of Professional Experience": 13,
        "Current Role/Position": "Horticultural consultant",
        "Dietary Requirements": "Halal",
        "Accessibility Requirements": "None",
        "Payment Method": "Bank Transfer",
        "Billing Address": "Unit 1699 Box 1436\nDPO AE 45119",
        "What do you hope to learn from this workshop?": "I am interested in exploring financial tools and models that can help optimize business growth.",
        "Any other special requests or comments?": "It would be beneficial to include some practical advice on managing financial risks and investments."
    },
    {
        "Full Name": "Ashley Strickland",
        "Email Address": "cindy32@hotmail.com",
        "Phone Number": "553.225.8986",
        "Organization/Company": "Tanner Group",
        "Workshop Category": "Digital Marketing",
        "Preferred Session Date": "2025/01/16",
        "Preferred Time Slot": "morning",
        "Preferred Delivery Mode": "Online",
        "Highest Education Level": "PhD",
        "Years of Professional Experience": 25,
        "Current Role/Position": "Mental health nurse",
        "Dietary Requirements": "Vegetarian",
        "Accessibility Requirements": "None",
        "Payment Method": "Company Sponsored",
        "Billing Address": "12794 Zamora Village Apt. 005\nPort Tammy, NE 09683",
        "What do you hope to learn from this workshop?": "I wish to learn more about how to manage and lead teams in dynamic work environments.",
        "Any other special requests or comments?": "I would prefer to focus on team-building strategies and techniques that can improve collaboration in diverse teams."
    },
    {
        "Full Name": "Stephanie Armstrong",
        "Email Address": "stephaniegalloway@hotmail.com",
        "Phone Number": "(106)562-3944x2227",
        "Organization/Company": "Wilson-Morton",
        "Workshop Category": "Business & Management",
        "Preferred Session Date": "2025/01/29",
        "Preferred Time Slot": "5PM",
        "Preferred Delivery Mode": "Online",
        "Highest Education Level": "Master's Degree",
        "Years of Professional Experience": 9,
        "Current Role/Position": "Jewellery designer",
        "Dietary Requirements": "None",
        "Accessibility Requirements": "None",
        "Payment Method": "Bank Transfer",
        "Billing Address": "PSC 7950, Box 5464\nAPO AA 57478",
        "What do you hope to learn from this workshop?": "I am looking forward to learning the latest trends in IT management and how to integrate them into our business.",
        "Any other special requests or comments?": "It would be helpful if we could have some materials to review after the workshop to continue learning."
    },
    {
        "Full Name": "David Green",
        "Email Address": "uconway@rodriguez.org",
        "Phone Number": "671.885.1473x24768",
        "Organization/Company": "Garcia, Smith and Klein",
        "Workshop Category": "Leadership & Communication",
        "Preferred Session Date": "2025/02/11",
        "Preferred Time Slot": "evening",
        "Preferred Delivery Mode": "In-Person",
        "Highest Education Level": "High School",
        "Years of Professional Experience": 9,
        "Current Role/Position": "Industrial/product designer",
        "Dietary Requirements": "Kosher",
        "Accessibility Requirements": "None",
        "Payment Method": "Bank Transfer",
        "Billing Address": "191 Willis Passage\nMonicastad, AK 72242",
        "What do you hope to learn from this workshop?": "I look forward to learning effective strategies for improving productivity and leading successful teams.",
        "Any other special requests or comments?": "I am particularly interested in hands-on learning opportunities and would prefer an interactive format."
    },
    {
        "Full Name": "Nathan Allen",
        "Email Address": "amandafloyd@hotmail.com",
        "Phone Number": "(184)631-0661x46800",
        "Organization/Company": "Glenn Ltd",
        "Workshop Category": "Finance & Investment",
        "Preferred Session Date": "2025/02/03",
        "Preferred Time Slot": "afternoon",
        "Preferred Delivery Mode": "Hybrid",
        "Highest Education Level": "Associate Degree",
        "Years of Professional Experience": 12,
        "Current Role/Position": "Engineer, manufacturing",
        "Dietary Requirements": "None",
        "Accessibility Requirements": "None",
        "Payment Method": "Company Sponsored",
        "Billing Address": "2946 Helen Unions Suite 122\nDavisfort, ND 66679",
        "What do you hope to learn from this workshop?": "I wish to learn more about how to manage and lead teams in dynamic work environments.",
        "Any other special requests or comments?": "I would like to see examples of successful leadership strategies in small and medium-sized businesses."
    },
    {
        "Full Name": "Gregory Chen",
        "Email Address": "jessehanson@yahoo.com",
        "Phone Number": "356-075-7766",
        "Organization/Company": "Horn PLC",
        "Workshop Category": "Finance & Investment",
        "Preferred Session Date": "2025/02/06",
        "Preferred Time Slot": "3PM",
        "Preferred Delivery Mode": "In-Person",
        "Highest Education Level": "High School",
        "Years of Professional Experience": 8,
        "Current Role/Position": "Physiological scientist",
        "Dietary Requirements": "Vegan",
        "Accessibility Requirements": "None",
        "Payment Method": "Company Sponsored",
        "Billing Address": "2639 Espinoza Crossroad Apt. 231\nPort Ryan, GA 12529",
        "What do you hope to learn from this workshop?": "I am excited to learn new skills in business management to better handle operational challenges.",
        "Any other special requests or comments?": "It would be great to have some discussions on how to scale business operations while maintaining a strong company culture."
    },
    {
        "Full Name": "John Smith",
        "Email Address": "kpatel@jackson-reynolds.com",
        "Phone Number": "+1-085-977-1757x8463",
        "Organization/Company": "Campbell and Sons",
        "Workshop Category": "Finance & Investment",
        "Preferred Session Date": "2025/01/12",
        "Preferred Time Slot": "9AM",
        "Preferred Delivery Mode": "Hybrid",
        "Highest Education Level": "High School",
        "Years of Professional Experience": 6,
        "Current Role/Position": "Equality and diversity officer",
        "Dietary Requirements": "Vegetarian",
        "Accessibility Requirements": "None",
        "Payment Method": "Bank Transfer",
        "Billing Address": "521 Davis Place Suite 437\nBrianmouth, AK 42938",
        "What do you hope to learn from this workshop?": "I would like to improve my leadership and communication skills to manage my team more effectively.",
        "Any other special requests or comments?": "I would like to see examples of successful leadership strategies in small and medium-sized businesses."
    },
    {
        "Full Name": "Jacob Olson",
        "Email Address": "blairwilliam@hotmail.com",
        "Phone Number": "425-997-3888",
        "Organization/Company": "Richard, Berger and Mcneil",
        "Workshop Category": "Technology & IT",
        "Preferred Session Date": "2025/01/04",
        "Preferred Time Slot": "3PM",
        "Preferred Delivery Mode": "Online",
        "Highest Education Level": "Master's Degree",
        "Years of Professional Experience": 16,
        "Current Role/Position": "Data scientist",
        "Dietary Requirements": "Kosher",
        "Accessibility Requirements": "None",
        "Payment Method": "Credit Card",
        "Billing Address": "1478 Bradley Fork Suite 247\nNew Danielland, ND 36498",
        "What do you hope to learn from this workshop?": "I am excited to learn new skills in business management to better handle operational challenges.",
        "Any other special requests or comments?": "I am particularly interested in hands-on learning opportunities and would prefer an interactive format."
    },
    {
        "Full Name": "Robert Johnson",
        "Email Address": "jacobwhite@barnes-mann.com",
        "Phone Number": "590.269.3295x7833",
        "Organization/Company": "Fisher-Diaz",
        "Workshop Category": "Digital Marketing",
        "Preferred Session Date": "2025/02/07",
        "Preferred Time Slot": "morning",
        "Preferred Delivery Mode": "Hybrid",
        "Highest Education Level": "Associate Degree",
        "Years of Professional Experience": 7,
        "Current Role/Position": "Architect",
        "Dietary Requirements": "Halal",
        "Accessibility Requirements": "None",
        "Payment Method": "Company Sponsored",
        "Billing Address": "069 Drew Extensions Apt. 645\nNorth Laurie, CT 58580",
        "What do you hope to learn from this workshop?": "I would like to improve my leadership and communication skills to manage my team more effectively.",
        "Any other special requests or comments?": "Please consider providing more information on the practical applications of digital marketing in different industries."
    },
    {
        "Full Name": "John Jennings",
        "Email Address": "tiffany14@hotmail.com",
        "Phone Number": "(081)816-7612",
        "Organization/Company": "Moore PLC",
        "Workshop Category": "Digital Marketing",
        "Preferred Session Date": "2025/01/28",
        "Preferred Time Slot": "11AM",
        "Preferred Delivery Mode": "Hybrid",
        "Highest Education Level": "Bachelor's Degree",
        "Years of Professional Experience": 12,
        "Current Role/Position": "Teacher, adult education",
        "Dietary Requirements": "None",
        "Accessibility Requirements": "None",
        "Payment Method": "Company Sponsored",
        "Billing Address": "940 Mary Trafficway\nChristopherside, MS 98413",
        "What do you hope to learn from this workshop?": "I wish to learn more about how to manage and lead teams in dynamic work environments.",
        "Any other special requests or comments?": "I am particularly interested in understanding how to develop an effective digital marketing strategy for a startup."
    },
    {
        "Full Name": "Daniel Medina",
        "Email Address": "daniel85@yahoo.com",
        "Phone Number": "422.722.3386x2996",
        "Organization/Company": "Miles and Sons",
        "Workshop Category": "Leadership & Communication",
        "Preferred Session Date": "2025/01/27",
        "Preferred Time Slot": "1PM",
        "Preferred Delivery Mode": "In-Person",
        "Highest Education Level": "Bachelor's Degree",
        "Years of Professional Experience": 18,
        "Current Role/Position": "Petroleum engineer",
        "Dietary Requirements": "Other (Please specify)",
        "Accessibility Requirements": "None",
        "Payment Method": "Company Sponsored",
        "Billing Address": "092 Moore Plains\nNorth Zachary, SC 42048",
        "What do you hope to learn from this workshop?": "I am excited to learn new skills in business management to better handle operational challenges.",
        "Any other special requests or comments?": "I would appreciate it if the workshop could include some real-life case studies or examples."
    },
    {
        "Full Name": "Debra Ruiz",
        "Email Address": "woodsleah@campbell.com",
        "Phone Number": "001-452-071-0611",
        "Organization/Company": "Calhoun Ltd",
        "Workshop Category": "Digital Marketing",
        "Preferred Session Date": "2025/01/09",
        "Preferred Time Slot": "9AM",
        "Preferred Delivery Mode": "Online",
        "Highest Education Level": "Master's Degree",
        "Years of Professional Experience": 16,
        "Current Role/Position": "Engineer, manufacturing",
        "Dietary Requirements": "None",
        "Accessibility Requirements": "None",
        "Payment Method": "Company Sponsored",
        "Billing Address": "USCGC Franco\nFPO AA 80636",
        "What do you hope to learn from this workshop?": "I am excited to learn new skills in business management to better handle operational challenges.",
        "Any other special requests or comments?": "I would appreciate it if the workshop could include some real-life case studies or examples."
    },
    {
        "Full Name": "Joan Hicks",
        "Email Address": "hernandezsara@hotmail.com",
        "Phone Number": "+1-272-070-9662x174",
        "Organization/Company": "Peterson PLC",
        "Workshop Category": "Finance & Investment",
        "Preferred Session Date": "2025/01/17",
        "Preferred Time Slot": "4PM",
        "Preferred Delivery Mode": "Online",
        "Highest Education Level": "Master's Degree",
        "Years of Professional Experience": 23,
        "Current Role/Position": "Prison officer",
        "Dietary Requirements": "None",
        "Accessibility Requirements": "None",
        "Payment Method": "Bank Transfer",
        "Billing Address": "454 Christine Junctions\nDenisetown, IN 41386",
        "What do you hope to learn from this workshop?": "I want to enhance my digital marketing knowledge to build stronger brand strategies and reach a wider audience.",
        "Any other special requests or comments?": "It would be great to have some discussions on how to scale business operations while maintaining a strong company culture."
    },
    {
        "Full Name": "Benjamin Castro",
        "Email Address": "melissadaniel@gmail.com",
        "Phone Number": "(107)707-7506x3492",
        "Organization/Company": "Martin Group",
        "Workshop Category": "Leadership & Communication",
        "Preferred Session Date": "2025/02/07",
        "Preferred Time Slot": "afternoon",
        "Preferred Delivery Mode": "Hybrid",
        "Highest Education Level": "Master's Degree",
        "Years of Professional Experience": 12,
        "Current Role/Position": "Cytogeneticist",
        "Dietary Requirements": "Other (Please specify)",
        "Accessibility Requirements": "None",
        "Payment Method": "Company Sponsored",
        "Billing Address": "142 John Dale Apt. 485\nCookberg, ND 61346",
        "What do you hope to learn from this workshop?": "I hope to gain a deeper understanding of digital marketing strategies to improve our company's online presence.",
        "Any other special requests or comments?": "I am particularly interested in hands-on learning opportunities and would prefer an interactive format."
    },
    {
        "Full Name": "Dana Peters",
        "Email Address": "michaelfoster@yahoo.com",
        "Phone Number": "2097511612",
        "Organization/Company": "Dixon Ltd",
        "Workshop Category": "Finance & Investment",
        "Preferred Session Date": "2025/01/06",
        "Preferred Time Slot": "8PM",
        "Preferred Delivery Mode": "Hybrid",
        "Highest Education Level": "PhD",
        "Years of Professional Experience": 14,
        "Current Role/Position": "Electronics engineer",
        "Dietary Requirements": "None",
        "Accessibility Requirements": "None",
        "Payment Method": "Company Sponsored",
        "Billing Address": "5400 Gross Road Suite 621\nSmithberg, NY 97557",
        "What do you hope to learn from this workshop?": "I wish to learn more about how to manage and lead teams in dynamic work environments.",
        "Any other special requests or comments?": "It would be great if we could have a session on the integration of modern technologies with traditional business models."
    },
    {
        "Full Name": "Kathleen Bell",
        "Email Address": "perezcaroline@rosales.biz",
        "Phone Number": "521.358.9633x55277",
        "Organization/Company": "Crane and Sons",
        "Workshop Category": "Leadership & Communication",
        "Preferred Session Date": "2025/01/11",
        "Preferred Time Slot": "12PM",
        "Preferred Delivery Mode": "Hybrid",
        "Highest Education Level": "Bachelor's Degree",
        "Years of Professional Experience": 11,
        "Current Role/Position": "Management consultant",
        "Dietary Requirements": "Vegan",
        "Accessibility Requirements": "None",
        "Payment Method": "Company Sponsored",
        "Billing Address": "31115 Leslie Ford\nHowardmouth, HI 75771",
        "What do you hope to learn from this workshop?": "I hope to acquire knowledge about investment strategies and financial planning for better decision-making in business.",
        "Any other special requests or comments?": "I would like to see examples of successful leadership strategies in small and medium-sized businesses."
    },
    {
        "Full Name": "Christine Lopez",
        "Email Address": "stoutsuzanne@ward.info",
        "Phone Number": "(516)362-2018x3914",
        "Organization/Company": "Payne, Rodriguez and Wilson",
        "Workshop Category": "Leadership & Communication",
        "Preferred Session Date": "2025/02/16",
        "Preferred Time Slot": "9PM",
        "Preferred Delivery Mode": "In-Person",
        "Highest Education Level": "Bachelor's Degree",
        "Years of Professional Experience": 13,
        "Current Role/Position": "Teacher, English as a foreign language",
        "Dietary Requirements": "Halal",
        "Accessibility Requirements": "None",
        "Payment Method": "Credit Card",
        "Billing Address": "164 Gomez Pass\nNorth Alanfort, DE 24988",
        "What do you hope to learn from this workshop?": "I am interested in exploring financial tools and models that can help optimize business growth.",
        "Any other special requests or comments?": "It would be great if we could have a session on the integration of modern technologies with traditional business models."
    },
    {
        "Full Name": "Michael Spencer",
        "Email Address": "charles95@ramsey.com",
        "Phone Number": "828.789.6269x117",
        "Organization/Company": "Zuniga Group",
        "Workshop Category": "Technology & IT",
        "Preferred Session Date": "2025/01/29",
        "Preferred Time Slot": "11AM",
        "Preferred Delivery Mode": "In-Person",
        "Highest Education Level": "Associate Degree",
        "Years of Professional Experience": 12,
        "Current Role/Position": "Scientist, biomedical",
        "Dietary Requirements": "Kosher",
        "Accessibility Requirements": "None",
        "Payment Method": "Company Sponsored",
        "Billing Address": "58019 Campbell Lodge\nWest Jeffrey, AL 54383",
        "What do you hope to learn from this workshop?": "I am excited to learn new skills in business management to better handle operational challenges.",
        "Any other special requests or comments?": "It would be beneficial to include some practical advice on managing financial risks and investments."
    },
    {
        "Full Name": "Catherine Baker",
        "Email Address": "kevin95@avila.com",
        "Phone Number": "401-666-0245x76845",
        "Organization/Company": "Mclaughlin-Wyatt",
        "Workshop Category": "Digital Marketing",
        "Preferred Session Date": "2025/01/10",
        "Preferred Time Slot": "5PM",
        "Preferred Delivery Mode": "Hybrid",
        "Highest Education Level": "Master's Degree",
        "Years of Professional Experience": 17,
        "Current Role/Position": "Outdoor activities/education manager",
        "Dietary Requirements": "Other (Please specify)",
        "Accessibility Requirements": "None",
        "Payment Method": "Company Sponsored",
        "Billing Address": "40056 James Forge Suite 454\nNew Ashley, NH 82795",
        "What do you hope to learn from this workshop?": "I am excited to learn new skills in business management to better handle operational challenges.",
        "Any other special requests or comments?": "It would be beneficial to include some practical advice on managing financial risks and investments."
    },
    {
        "Full Name": "Darren Beltran",
        "Email Address": "adammoore@stevens.net",
        "Phone Number": "585-402-7685",
        "Organization/Company": "White-Rodriguez",
        "Workshop Category": "Leadership & Communication",
        "Preferred Session Date": "2025/01/01",
        "Preferred Time Slot": "5PM",
        "Preferred Delivery Mode": "Hybrid",
        "Highest Education Level": "High School",
        "Years of Professional Experience": 12,
        "Current Role/Position": "Museum education officer",
        "Dietary Requirements": "Vegetarian",
        "Accessibility Requirements": "None",
        "Payment Method": "Credit Card",
        "Billing Address": "91643 Mark Point Suite 351\nNew Robin, SC 94431",
        "What do you hope to learn from this workshop?": "I hope to gain a deeper understanding of digital marketing strategies to improve our company's online presence.",
        "Any other special requests or comments?": "Please consider providing more information on the practical applications of digital marketing in different industries."
    },
    {
        "Full Name": "Michael Frazier",
        "Email Address": "breweramber@yahoo.com",
        "Phone Number": "(200)051-5968x760",
        "Organization/Company": "Banks, Dunlap and Chavez",
        "Workshop Category": "Technology & IT",
        "Preferred Session Date": "2025/01/24",
        "Preferred Time Slot": "9AM",
        "Preferred Delivery Mode": "In-Person",
        "Highest Education Level": "PhD",
        "Years of Professional Experience": 11,
        "Current Role/Position": "Medical secretary",
        "Dietary Requirements": "Vegan",
        "Accessibility Requirements": "None",
        "Payment Method": "Company Sponsored",
        "Billing Address": "84490 Laura Loop\nSouth Scott, MN 98569",
        "What do you hope to learn from this workshop?": "I am excited to learn new skills in business management to better handle operational challenges.",
        "Any other special requests or comments?": "It would be beneficial to include some practical advice on managing financial risks and investments."
    }
]